{"numFound": 48, "start": 0, "numFoundExact": true, "docs": [{"alternate_names": ["Christopher Tolkien", "Christopher Reuel Tolkien", "Christopher (Ed) Tolkien"], "birth_date": "21 November 1924", "death_date": "16 January 2020", "key": "OL2623360A", "name": "Christopher Tolkien", "top_subjects": ["Middle earth (imaginary place), fiction", "Middle Earth (Imaginary place)", "Fiction, fantasy, general", "Tolkien, j, r. r. (john ronald ruel), 1892-1973", "Middle earth (imaginary place)", "British and irish fiction (fictional works by one author)", "Fiction, fantasy, epic", "Fiction, fantasy, historical", "Fantasy fiction, history and criticism", "English Fantasy fiction"], "top_work": "The Shaping of Middle-Earth: the Quenta, the Ambarkanta, and the annals, together with the earliest 'Silmarillion' and the first map", "type": "author", "work_count": 40, "ratings_average": 4.111111, "ratings_sortable": 3.2198472, "ratings_count": 9, "ratings_count_1": 0, "ratings_count_2": 0, "ratings_count_3": 2, "ratings_count_4": 4, "ratings_count_5": 3, "want_to_read_count": 209, "already_read_count": 20, "currently_reading_count": 5, "readinglog_count": 234, "_version_": 1826756816865853444}, {"key": "OL14431239A", "name": "F. Tolkien", "top_work": "Thug Life", "type": "author", "work_count": 35, "ratings_average": 0.0, "ratings_sortable": 2.047372, "ratings_count": 0, "ratings_count_1": 0, "ratings_count_2": 0, "ratings_count_3": 0, "ratings_count_4": 0, "ratings_count_5": 0, "want_to_read_count": 0, "already_read_count": 0, "currently_reading_count": 0, "readinglog_count": 0, "_version_": 1826723003003568134}, {"alternate_names": ["John Ronald Reuel Tolkien", "Dzhon R. R. Tolkin", "Yue Han Luo Na De Rui Er Tuo Er Jin", "J. R. R. Tolkien", "John R. R. Tolkien", "Tolkien", "J. R.R. Tolkien", "J R R Tolkien", "J.R.R.Tolkien"], "birth_date": "3 January 1892", "death_date": "2 September 1973", "key": "OL26320A", "name": "J.R.R. Tolkien", "top_subjects": ["Middle Earth (Imaginary place)", "Middle earth (imaginary place), fiction", "British and irish fiction (fictional works by one author)", "Fiction, fantasy, general", "Fiction", "English Fantasy fiction", "History and criticism", "Fiction, fantasy, epic", "Tolkien, j, r. r. (john ronald ruel), 1892-1973", "English literature"], "top_work": "The Hobbit", "type": "author", "work_count": 317, "ratings_average": 4.2887516, "ratings_sortable": 4.243359, "ratings_count": 1458, "ratings_count_1": 30, "ratings_count_2": 50, "ratings_count_3": 172, "ratings_count_4": 423, "ratings_count_5": 783, "want_to_read_count": 9609, "already_read_count": 2390, "currently_reading_count": 657, "readinglog_count": 12656, "_version_": 1827206592743866369}, {"key": "OL13696562A", "name": "J. R. R. Tolkien", "top_subjects": ["Middle earth (imaginary place), fiction", "Gandalf (fictitious character), fiction", "Fiction, fantasy, general", "Fiction, fantasy, epic", "British and irish fiction (fictional works by one author)", "Baggins, bilbo (fictitious character), fiction"], "top_work": "Hobbit", "type": "author", "work_count": 27, "ratings_average": 0.0, "ratings_sortable": 2.047372, "ratings_count": 0, "ratings_count_1": 0, "ratings_count_2": 0, "ratings_count_3": 0, "ratings_count_4": 0, "ratings_count_5": 0, "want_to_read_count": 0, "already_read_count": 0, "currently_reading_count": 0, "readinglog_count": 0, "_version_": 1826713167176138753}, {"birth_date": "1959", "key": "OL1477672A", "name": "Simon Tolkien", "top_subjects": ["Fiction", "Fiction, legal", "Fiction, thrillers, suspense", "England, fiction", "Fiction, thrillers, general", "Crime, fiction", "Fiction, historical, general", "Fathers and sons, fiction", "Fathers and sons", "Crimes against"], "top_work": "Final Witness", "type": "author", "work_count": 18, "ratings_average": 0.0, "ratings_sortable": 2.047372, "ratings_count": 0, "ratings_count_1": 0, "ratings_count_2": 0, "ratings_count_3": 0, "ratings_count_4": 0, "ratings_count_5": 0, "want_to_read_count": 7, "already_read_count": 0, "currently_reading_count": 0, "readinglog_count": 7, "_version_": 1826728487502741504}, {"birth_date": "1892", "death_date": "1973", "key": "OL14008371A", "name": "J. R. R. Tolkien", "top_subjects": ["Middle Earth (Imaginary place)", "Linguistics", "Language", "J. R. R. Tolkien (1892-1973)", "Hobbits (Fictitious characters)", "Bilbo Baggins (Fictitious character)", "Quenya (Artificial language)", "Noun", "Imaginary languages in literature", "Declension"], "top_work": "The Fellowship of the Ring", "type": "author", "work_count": 11, "ratings_average": 0.0, "ratings_sortable": 2.047372, "ratings_count": 0, "ratings_count_1": 0, "ratings_count_2": 0, "ratings_count_3": 0, "ratings_count_4": 0, "ratings_count_5": 0, "want_to_read_count": 0, "already_read_count": 0, "currently_reading_count": 0, "readinglog_count": 0, "_version_": 1826719016712929284}, {"key": "OL2977155A", "name": "Michael Tolkien", "top_subjects": ["Fiction, fantasy, general", "Fiction, action & adventure", "Poetry (poetic works by one author)", "Fantasy fiction", "Children's fiction", "Adventure and adventurers, fiction"], "top_work": "Rainbow", "type": "author", "work_count": 8, "ratings_average": 0.0, "ratings_sortable": 2.047372, "ratings_count": 0, "ratings_count_1": 0, "ratings_count_2": 0, "ratings_count_3": 0, "ratings_count_4": 0, "ratings_count_5": 0, "want_to_read_count": 0, "already_read_count": 0, "currently_reading_count": 0, "readinglog_count": 0, "_version_": 1826762935198810116}, {"birth_date": "1962", "key": "OL38677A", "name": "Tracy Tolkien", "top_subjects": ["History", "Collectors and collecting", "Fashion", "Vintage clothing", "Costume jewelry", "20th century", "Catalogs", "Antiques/Collectibles", "Antiques / Collectibles", "Antiques & Collectibles / Jewelry"], "top_work": "A collector's guide to costume jewelry", "type": "author", "work_count": 7, "ratings_average": 5.0, "ratings_sortable": 2.4036636, "ratings_count": 1, "ratings_count_1": 0, "ratings_count_2": 0, "ratings_count_3": 0, "ratings_count_4": 0, "ratings_count_5": 1, "want_to_read_count": 12, "already_read_count": 1, "currently_reading_count": 0, "readinglog_count": 13, "_version_": 1826779096441421832}, {"key": "OL10273437A", "name": "Simon Tolkien", "top_subjects": ["Fiction, legal", "Trials (Murder)", "France, fiction", "Fiction, thrillers, suspense", "Fiction, psychological", "Fiction, crime", "Fiction", "Fathers and sons, fiction", "England, fiction", "Crime, fiction"], "top_work": "Room of Lost Steps", "type": "author", "work_count": 6, "ratings_average": 0.0, "ratings_sortable": 2.047372, "ratings_count": 0, "ratings_count_1": 0, "ratings_count_2": 0, "ratings_count_3": 0, "ratings_count_4": 0, "ratings_count_5": 0, "want_to_read_count": 0, "already_read_count": 0, "currently_reading_count": 0, "readinglog_count": 0, "_version_": 1826646078591598594}, {"key": "OL14454981A", "name": "F. U. N. Tolkien", "top_work": "Master of the Universe", "type": "author", "work_count": 6, "ratings_average": 0.0, "ratings_sortable": 2.047372, "ratings_count": 0, "ratings_count_1": 0, "ratings_count_2": 0, "ratings_count_3": 0, "ratings_count_4": 0, "ratings_count_5": 0, "want_to_read_count": 0, "already_read_count": 0, "currently_reading_count": 0, "readinglog_count": 0, "_version_": 1826724764522119169}, {"alternate_names": ["J. Kenneth Tolkien"], "birth_date": "1881", "death_date": "1935", "key": "OL2447931A", "name": "James Kenneth Tolkien", "top_subjects": ["Po\u00e9sie canadienne-anglaise, ICMH", "Canadian poetry (English), CIHM"], "top_work": "The inn of Gahnobway: [poems]", "type": "author", "work_count": 3, "ratings_average": 0.0, "ratings_sortable": 2.047372, "ratings_count": 0, "ratings_count_1": 0, "ratings_count_2": 0, "ratings_count_3": 0, "ratings_count_4": 0, "ratings_count_5": 0, "want_to_read_count": 0, "already_read_count": 0, "currently_reading_count": 0, "readinglog_count": 0, "_version_": 1826753826634334213}, {"birth_date": "1943", "key": "OL12057534A", "name": "Michael Tolkien", "top_subjects": ["English poetry", "21st century"], "top_work": "Exposures", "type": "author", "work_count": 2, "ratings_average": 0.0, "ratings_sortable": 2.047372, "ratings_count": 0, "ratings_count_1": 0, "ratings_count_2": 0, "ratings_count_3": 0, "ratings_count_4": 0, "ratings_count_5": 0, "want_to_read_count": 0, "already_read_count": 0, "currently_reading_count": 0, "readinglog_count": 0, "_version_": 1826682038109863942}, {"key": "OL14991321A", "name": "Christopher Tolkien", "top_work": "Tree and Leaf", "type": "author", "work_count": 2, "ratings_average": 0.0, "ratings_sortable": 2.047372, "ratings_count": 0, "ratings_count_1": 0, "ratings_count_2": 0, "ratings_count_3": 0, "ratings_count_4": 0, "ratings_count_5": 0, "want_to_read_count": 0, "already_read_count": 0, "currently_reading_count": 0, "readinglog_count": 0, "_version_": 1826735834794033162}, {"key": "OL7925803A", "name": "Hartmut Tolkien", "top_work": "Schmierwirkungen in Schmiedegesenken", "type": "author", "work_count": 2, "ratings_average": 0.0, "ratings_sortable": 2.047372, "ratings_count": 0, "ratings_count_1": 0, "ratings_count_2": 0, "ratings_count_3": 0, "ratings_count_4": 0, "ratings_count_5": 0, "want_to_read_count": 0, "already_read_count": 0, "currently_reading_count": 0, "readinglog_count": 0, "_version_": 1826850645139783680}, {"key": "OL15445861A", "name": "Tolkien", "type": "author", "work_count": 0, "ratings_average": 0.0, "ratings_sortable": 2.047372, "ratings_count": 0, "ratings_count_1": 0, "ratings_count_2": 0, "ratings_count_3": 0, "ratings_count_4": 0, "ratings_count_5": 0, "want_to_read_count": 0, "already_read_count": 0, "currently_reading_count": 0, "readinglog_count": 0, "_version_": 1831775148846350336}, {"key": "OL14508282A", "name": "F. U. N. Tolkien Notebooks", "top_work": "Yoga", "type": "author", "work_count": 3, "ratings_average": 0.0, "ratings_sortable": 2.047372, "ratings_count": 0, "ratings_count_1": 0, "ratings_count_2": 0, "ratings_count_3": 0, "ratings_count_4": 0, "ratings_count_5": 0, "want_to_read_count": 0, "already_read_count": 0, "currently_reading_count": 0, "readinglog_count": 0, "_version_": 1826727027976175616}, {"key": "OL13717765A", "name": "Tom Tolkien", "top_work": "Mirages", "type": "author", "work_count": 1, "ratings_average": 0.0, "ratings_sortable": 2.047372, "ratings_count": 0, "ratings_count_1": 0, "ratings_count_2": 0, "ratings_count_3": 0, "ratings_count_4": 0, "ratings_count_5": 0, "want_to_read_count": 0, "already_read_count": 0, "currently_reading_count": 0, "readinglog_count": 0, "_version_": 1826711155371933700}, {"key": "OL14499862A", "name": "Dzon Tolkien", "top_work": "Hobit", "type": "author", "work_count": 1, "ratings_average": 0.0, "ratings_sortable": 2.047372, "ratings_count": 0, "ratings_count_1": 0, "ratings_count_2": 0, "ratings_count_3": 0, "ratings_count_4": 0, "ratings_count_5": 0, "want_to_read_count": 0, "already_read_count": 0, "currently_reading_count": 0, "readinglog_count": 0, "_version_": 1826727315604766728}, {"key": "OL14699176A", "name": "Ed Tolkien", "top_work": "Simple Sourdoughs", "type": "author", "work_count": 1, "ratings_average": 0.0, "ratings_sortable": 2.047372, "ratings_count": 0, "ratings_count_1": 0, "ratings_count_2": 0, "ratings_count_3": 0, "ratings_count_4": 0, "ratings_count_5": 0, "want_to_read_count": 0, "already_read_count": 0, "currently_reading_count": 0, "readinglog_count": 0, "_version_": 1826729686439297027}, {"key": "OL12796824A", "name": "Tolkien Simon", "top_work": "De stiefmoeder", "type": "author", "work_count": 1, "ratings_average": 0.0, "ratings_sortable": 2.047372, "ratings_count": 0, "ratings_count_1": 0, "ratings_count_2": 0, "ratings_count_3": 0, "ratings_count_4": 0, "ratings_count_5": 0, "want_to_read_count": 0, "already_read_count": 0, "currently_reading_count": 0, "readinglog_count": 0, "_version_": 1826694430437933059}, {"birth_date": "1917", "key": "OL676461A", "name": "John Tolkien", "top_work": "The Tolkien family album", "type": "author", "work_count": 1, "ratings_average": 0.0, "ratings_sortable": 2.047372, "ratings_count": 0, "ratings_count_1": 0, "ratings_count_2": 0, "ratings_count_3": 0, "ratings_count_4": 0, "ratings_count_5": 0, "want_to_read_count": 2, "already_read_count": 0, "currently_reading_count": 1, "readinglog_count": 3, "_version_": 1826832417635172352}, {"key": "OL9692672A", "name": "Hilary Tolkien", "top_subjects": ["Fiction, historical, general", "Biography"], "top_work": "Black and White Ogre Country de Luxe Edition", "type": "author", "work_count": 1, "ratings_average": 0.0, "ratings_sortable": 2.047372, "ratings_count": 0, "ratings_count_1": 0, "ratings_count_2": 0, "ratings_count_3": 0, "ratings_count_4": 0, "ratings_count_5": 0, "want_to_read_count": 0, "already_read_count": 0, "currently_reading_count": 0, "readinglog_count": 0, "_version_": 1826884066495954950}, {"key": "OL6206934A", "name": "Susan Tolkien", "top_work": "The performance of gel entrapped Streptomyces clavuligerus producing clavulanic acid", "type": "author", "work_count": 1, "ratings_average": 0.0, "ratings_sortable": 2.047372, "ratings_count": 0, "ratings_count_1": 0, "ratings_count_2": 0, "ratings_count_3": 0, "ratings_count_4": 0, "ratings_count_5": 0, "want_to_read_count": 0, "already_read_count": 0, "currently_reading_count": 0, "readinglog_count": 0, "_version_": 1826822224730914822}, {"key": "OL12409183A", "name": "George Tolkien", "top_work": "Hinduism", "type": "author", "work_count": 1, "ratings_average": 0.0, "ratings_sortable": 2.047372, "ratings_count": 0, "ratings_count_1": 0, "ratings_count_2": 0, "ratings_count_3": 0, "ratings_count_4": 0, "ratings_count_5": 0, "want_to_read_count": 0, "already_read_count": 0, "currently_reading_count": 0, "readinglog_count": 0, "_version_": 1826688606796775424}, {"key": "OL9300335A", "name": "Nicholas Tolkien", "top_work": "The Thing In Packy Innard\u2019s Place", "type": "author", "work_count": 1, "ratings_average": 0.0, "ratings_sortable": 2.047372, "ratings_count": 0, "ratings_count_1": 0, "ratings_count_2": 0, "ratings_count_3": 0, "ratings_count_4": 0, "ratings_count_5": 0, "want_to_read_count": 0, "already_read_count": 0, "currently_reading_count": 0, "readinglog_count": 0, "_version_": 1826876460498944012}, {"key": "OL9292353A", "name": "Royd Tolkien", "top_work": "There's a Hole in my Bucket", "type": "author", "work_count": 1, "ratings_average": 0.0, "ratings_sortable": 2.047372, "ratings_count": 0, "ratings_count_1": 0, "ratings_count_2": 0, "ratings_count_3": 0, "ratings_count_4": 0, "ratings_count_5": 0, "want_to_read_count": 2, "already_read_count": 0, "currently_reading_count": 0, "readinglog_count": 2, "_version_": 1826876796312748038}, {"key": "OL14056242A", "name": "J. R. R. (John Ronald Reuel) Tolkien", "top_work": "Fellowship of the Ring", "type": "author", "work_count": 3, "ratings_average": 0.0, "ratings_sortable": 2.047372, "ratings_count": 0, "ratings_count_1": 0, "ratings_count_2": 0, "ratings_count_3": 0, "ratings_count_4": 0, "ratings_count_5": 0, "want_to_read_count": 1, "already_read_count": 0, "currently_reading_count": 0, "readinglog_count": 1, "_version_": 1826717092330602501}, {"key": "OL13752614A", "name": "by Tom Tolkien", "top_work": "M I R a G e S Tom Tolkien", "type": "author", "work_count": 1, "ratings_average": 0.0, "ratings_sortable": 2.047372, "ratings_count": 0, "ratings_count_1": 0, "ratings_count_2": 0, "ratings_count_3": 0, "ratings_count_4": 0, "ratings_count_5": 0, "want_to_read_count": 0, "already_read_count": 0, "currently_reading_count": 0, "readinglog_count": 0, "_version_": 1826713561283428354}, {"key": "OL13576713A", "name": "I. Kenneth Tolkien", "top_work": "Inn of Gahnobway", "type": "author", "work_count": 1, "ratings_average": 0.0, "ratings_sortable": 2.047372, "ratings_count": 0, "ratings_count_1": 0, "ratings_count_2": 0, "ratings_count_3": 0, "ratings_count_4": 0, "ratings_count_5": 0, "want_to_read_count": 0, "already_read_count": 0, "currently_reading_count": 0, "readinglog_count": 0, "_version_": 1826708847557869575}, {"key": "OL5886663A", "name": "Tolkien Society. Workshop", "top_subjects": ["Fiction, fantasy, collections & anthologies", "Congresses"], "top_work": "Leaves from the tree", "type": "author", "work_count": 1, "ratings_average": 0.0, "ratings_sortable": 2.047372, "ratings_count": 0, "ratings_count_1": 0, "ratings_count_2": 0, "ratings_count_3": 0, "ratings_count_4": 0, "ratings_count_5": 0, "want_to_read_count": 0, "already_read_count": 0, "currently_reading_count": 0, "readinglog_count": 0, "_version_": 1826815820663095298}, {"key": "OL7427087A", "name": "J. Kenneth Tolkien", "top_work": "The inn of Gahnobway", "type": "author", "work_count": 1, "ratings_average": 0.0, "ratings_sortable": 2.047372, "ratings_count": 0, "ratings_count_1": 0, "ratings_count_2": 0, "ratings_count_3": 0, "ratings_count_4": 0, "ratings_count_5": 0, "want_to_read_count": 0, "already_read_count": 0, "currently_reading_count": 0, "readinglog_count": 0, "_version_": 1826844085833433090}, {"key": "OL15481301A", "name": "J. R.R. TOLKIEN", "top_work": "THE TWO TOWERS BIENG THE SECOND PART OF THE LORD OF THE RINGS", "type": "author", "work_count": 1, "ratings_average": 0.0, "ratings_sortable": 2.047372, "ratings_count": 0, "ratings_count_1": 0, "ratings_count_2": 0, "ratings_count_3": 0, "ratings_count_4": 0, "ratings_count_5": 0, "want_to_read_count": 0, "already_read_count": 0, "currently_reading_count": 0, "readinglog_count": 0, "_version_": 1832180658610372608}, {"key": "OL8362990A", "name": "Baillie Tolkien", "type": "author", "work_count": 0, "ratings_average": 0.0, "ratings_sortable": 2.047372, "ratings_count": 0, "ratings_count_1": 0, "ratings_count_2": 0, "ratings_count_3": 0, "ratings_count_4": 0, "ratings_count_5": 0, "want_to_read_count": 0, "already_read_count": 0, "currently_reading_count": 0, "readinglog_count": 0, "_version_": 1826861809798217736}, {"key": "OL3128307A", "name": "Adam Tolkien", "type": "author", "work_count": 0, "ratings_average": 0.0, "ratings_sortable": 2.047372, "ratings_count": 0, "ratings_count_1": 0, "ratings_count_2": 0, "ratings_count_3": 0, "ratings_count_4": 0, "ratings_count_5": 0, "want_to_read_count": 0, "already_read_count": 0, "currently_reading_count": 0, "readinglog_count": 0, "_version_": 1826763444879097859}, {"key": "OL15378992A", "name": "j.r.r tolkien ", "type": "author", "work_count": 0, "ratings_average": 0.0, "ratings_sortable": 2.047372, "ratings_count": 0, "ratings_count_1": 0, "ratings_count_2": 0, "ratings_count_3": 0, "ratings_count_4": 0, "ratings_count_5": 0, "want_to_read_count": 0, "already_read_count": 0, "currently_reading_count": 0, "readinglog_count": 0, "_version_": 1830961367271604224}, {"key": "OL15303987A", "name": "Christopher Tolkien ", "type": "author", "work_count": 0, "ratings_average": 0.0, "ratings_sortable": 2.047372, "ratings_count": 0, "ratings_count_1": 0, "ratings_count_2": 0, "ratings_count_3": 0, "ratings_count_4": 0, "ratings_count_5": 0, "want_to_read_count": 0, "already_read_count": 0, "currently_reading_count": 0, "readinglog_count": 0, "_version_": 1830542364957999105}, {"key": "OL15333750A", "name": "J.R.R.  Tolkien ", "type": "author", "work_count": 0, "ratings_average": 0.0, "ratings_sortable": 2.047372, "ratings_count": 0, "ratings_count_1": 0, "ratings_count_2": 0, "ratings_count_3": 0, "ratings_count_4": 0, "ratings_count_5": 0, "want_to_read_count": 0, "already_read_count": 0, "currently_reading_count": 0, "readinglog_count": 0, "_version_": 1830615631807905795}, {"key": "OL15318536A", "name": "J.R.R. Tolkien ", "type": "author", "work_count": 0, "ratings_average": 0.0, "ratings_sortable": 2.047372, "ratings_count": 0, "ratings_count_1": 0, "ratings_count_2": 0, "ratings_count_3": 0, "ratings_count_4": 0, "ratings_count_5": 0, "want_to_read_count": 0, "already_read_count": 0, "currently_reading_count": 0, "readinglog_count": 0, "_version_": 1830572898518040583}, {"key": "OL15287647A", "name": "J.R.R. Tolkien", "type": "author", "work_count": 0, "ratings_average": 0.0, "ratings_sortable": 2.047372, "ratings_count": 0, "ratings_count_1": 0, "ratings_count_2": 0, "ratings_count_3": 0, "ratings_count_4": 0, "ratings_count_5": 0, "want_to_read_count": 0, "already_read_count": 0, "currently_reading_count": 0, "readinglog_count": 0, "_version_": 1830479939991764992}, {"key": "OL14497443A", "name": "J. R. R. Tolki\u00ebn", "top_work": "Lost Manuscript (or the Books of the Kings)", "type": "author", "work_count": 1, "ratings_average": 0.0, "ratings_sortable": 2.047372, "ratings_count": 0, "ratings_count_1": 0, "ratings_count_2": 0, "ratings_count_3": 0, "ratings_count_4": 0, "ratings_count_5": 0, "want_to_read_count": 0, "already_read_count": 0, "currently_reading_count": 0, "readinglog_count": 0, "_version_": 1826726463545540611}, {"key": "OL6522899A", "name": "Tolkien Society (England). Seminar", "top_subjects": ["Modern Literature", "Medieval influences", "Literature, Modern", "J. R. R. Tolkien (1892-1973)", "Influence", "History and criticism", "Fantasy fiction, English", "English Fantasy fiction", "Congresses", "20th century"], "top_work": "Tolkien", "type": "author", "work_count": 1, "ratings_average": 0.0, "ratings_sortable": 2.047372, "ratings_count": 0, "ratings_count_1": 0, "ratings_count_2": 0, "ratings_count_3": 0, "ratings_count_4": 0, "ratings_count_5": 0, "want_to_read_count": 0, "already_read_count": 0, "currently_reading_count": 0, "readinglog_count": 0, "_version_": 1826826632134918146}, {"key": "OL11273193A", "name": "Tolkien Charlotte Eric  Pixel  Sarah", "top_work": "Would You Rather Sour Edition", "type": "author", "work_count": 1, "ratings_average": 0.0, "ratings_sortable": 2.047372, "ratings_count": 0, "ratings_count_1": 0, "ratings_count_2": 0, "ratings_count_3": 0, "ratings_count_4": 0, "ratings_count_5": 0, "want_to_read_count": 0, "already_read_count": 0, "currently_reading_count": 0, "readinglog_count": 0, "_version_": 1826663517229416449}, {"key": "OL14680430A", "name": "J. J. R. R. Tolkien", "top_work": "Hobbit", "type": "author", "work_count": 1, "ratings_average": 0.0, "ratings_sortable": 2.047372, "ratings_count": 0, "ratings_count_1": 0, "ratings_count_2": 0, "ratings_count_3": 0, "ratings_count_4": 0, "ratings_count_5": 0, "want_to_read_count": 0, "already_read_count": 0, "currently_reading_count": 0, "readinglog_count": 0, "_version_": 1826729372431679491}, {"key": "OL14460018A", "name": "J. R. R. J.R.R. Tolkien", "top_work": "Two Towers", "type": "author", "work_count": 1, "ratings_average": 0.0, "ratings_sortable": 2.047372, "ratings_count": 0, "ratings_count_1": 0, "ratings_count_2": 0, "ratings_count_3": 0, "ratings_count_4": 0, "ratings_count_5": 0, "want_to_read_count": 0, "already_read_count": 0, "currently_reading_count": 0, "readinglog_count": 0, "_version_": 1826723650896658435}, {"key": "OL332676A", "name": "J. R. R. Tolkien Centenary Conference (1992 Keble College, Oxford)", "top_subjects": ["Middle Earth (Imaginary place)", "J. R. R. Tolkien (1892-1973)", "History and criticism", "Fantasy literature, English", "English Fantasy literature", "Criticism and interpretation", "Congresses", "Literary Criticism", "English literature, history and criticism, 20th century", "1892-1973"], "top_work": "Proceedings of the J.R.R. Tolkien Centenary Conference, 1992", "type": "author", "work_count": 2, "ratings_average": 0.0, "ratings_sortable": 2.047372, "ratings_count": 0, "ratings_count_1": 0, "ratings_count_2": 0, "ratings_count_3": 0, "ratings_count_4": 0, "ratings_count_5": 0, "want_to_read_count": 1, "already_read_count": 0, "currently_reading_count": 0, "readinglog_count": 1, "_version_": 1826768099111600133}, {"key": "OL12498774A", "name": "Wheeler, R.E.M. And Wheeler, T.V. (Tolkien, J.R.R., Essay By)", "top_work": "REPORT ON THE EXCAVATION OF THE PREHISTORIC, ROMAN AND POST-ROMAN SITE IN LYDNEY PARK GLOUCESTERSHIRE", "type": "author", "work_count": 1, "ratings_average": 0.0, "ratings_sortable": 2.047372, "ratings_count": 0, "ratings_count_1": 0, "ratings_count_2": 0, "ratings_count_3": 0, "ratings_count_4": 0, "ratings_count_5": 0, "want_to_read_count": 0, "already_read_count": 0, "currently_reading_count": 0, "readinglog_count": 0, "_version_": 1826690717716578305}, {"key": "OL11532768A", "name": "John R. Clark; Wrenn, C. L.; Tolkien, J. R. R. Hall", "top_work": "Beowulf and the Finnesburg Fragment", "type": "author", "work_count": 1, "ratings_average": 0.0, "ratings_sortable": 2.047372, "ratings_count": 0, "ratings_count_1": 0, "ratings_count_2": 0, "ratings_count_3": 0, "ratings_count_4": 0, "ratings_count_5": 0, "want_to_read_count": 0, "already_read_count": 0, "currently_reading_count": 0, "readinglog_count": 0, "_version_": 1826670316392284160}, {"key": "OL4501524A", "name": "Tolkien Festival (Oct. 28-29, 1966 Mankato State College, Mankato, Minnesota)", "top_subjects": ["J. R. R. Tolkien (1892-1973)"], "top_work": "The Tolkien papers", "type": "author", "work_count": 1, "ratings_average": 0.0, "ratings_sortable": 2.047372, "ratings_count": 0, "ratings_count_1": 0, "ratings_count_2": 0, "ratings_count_3": 0, "ratings_count_4": 0, "ratings_count_5": 0, "want_to_read_count": 0, "already_read_count": 0, "currently_reading_count": 0, "readinglog_count": 0, "_version_": 1826787315914113024}]}